llm_file_organizer/__init__.py
llm_file_organizer/__main__.py
llm_file_organizer/classifier.py
llm_file_organizer/cli.py
llm_file_organizer/config.py
llm_file_organizer/interactive.py
llm_file_organizer/organizer.py
llm_file_organizer/plan_manager.py
llm_file_organizer/scanner.py
llm_file_organizer-0.1.0.dist-info/METADATA
llm_file_organizer-0.1.0.dist-info/WHEEL
llm_file_organizer-0.1.0.dist-info/entry_points.txt
llm_file_organizer-0.1.0.dist-info/licenses/LICENSE
llm_file_organizer-0.1.0.dist-info/RECORD
