Metadata-Version: 2.4
Name: llm-file-organizer
Version: 0.1.0
Summary: AI-powered filesystem cleanup tool with interactive CLI
Project-URL: Homepage, https://github.com/moop6535/llm-file-organizer
Project-URL: Repository, https://github.com/moop6535/llm-file-organizer
Project-URL: Issues, https://github.com/moop6535/llm-file-organizer/issues
Author: Moop
License-Expression: MIT
License-File: LICENSE
Keywords: ai,anthropic,automation,cleanup,cli,files,filesystem,interactive,llm,ollama,openai,organizer
Classifier: Development Status :: 4 - Beta
Classifier: Environment :: Console
Classifier: Intended Audience :: Developers
Classifier: Intended Audience :: End Users/Desktop
Classifier: License :: OSI Approved :: MIT License
Classifier: Operating System :: OS Independent
Classifier: Programming Language :: Python :: 3
Classifier: Programming Language :: Python :: 3.10
Classifier: Programming Language :: Python :: 3.11
Classifier: Programming Language :: Python :: 3.12
Classifier: Programming Language :: Python :: 3.13
Classifier: Topic :: Desktop Environment :: File Managers
Classifier: Topic :: System :: Filesystems
Classifier: Topic :: Utilities
Requires-Python: >=3.10
Requires-Dist: inquirerpy>=0.3.0
Requires-Dist: python-dotenv>=1.0.0
Requires-Dist: rich>=13.0.0
Provides-Extra: all
Requires-Dist: anthropic>=0.30.0; extra == 'all'
Requires-Dist: httpx>=0.25.0; extra == 'all'
Requires-Dist: openai>=1.0.0; extra == 'all'
Provides-Extra: anthropic
Requires-Dist: anthropic>=0.30.0; extra == 'anthropic'
Provides-Extra: dev
Requires-Dist: mypy>=1.0.0; extra == 'dev'
Requires-Dist: pytest-cov>=4.0.0; extra == 'dev'
Requires-Dist: pytest>=7.0.0; extra == 'dev'
Requires-Dist: ruff>=0.1.0; extra == 'dev'
Provides-Extra: ollama
Requires-Dist: httpx>=0.25.0; extra == 'ollama'
Provides-Extra: openai
Requires-Dist: openai>=1.0.0; extra == 'openai'
